it/__init__.py
it/si3p/__init__.py
it/si3p/supwsd/__init__.py
it/si3p/supwsd/analysis.py
it/si3p/supwsd/api.py
it/si3p/supwsd/config.py
supwsd/__init__.py
supwsd/app.py
supwsd/model.py
supwsd/params.py
supwsd/service.py
supwsd/wsd.py
supwsd-1.2.9.dist-info/LICENSE.txt
supwsd-1.2.9.dist-info/METADATA
supwsd-1.2.9.dist-info/WHEEL
supwsd-1.2.9.dist-info/top_level.txt
supwsd-1.2.9.dist-info/RECORD
