Metadata-Version: 2.1
Name: supwsd
Version: 1.2.9
Summary: Python binding to the SupWSD RESTful service.
Home-page: https://supwsd.net
Author: Simone Papandrea
Author-email: papandrea.simone@gmail.com
License: CC BY-NC-SA 3.0
Keywords: Supervised Word Sense Disambiguation Translation
Platform: UNKNOWN
Classifier: Programming Language :: Python :: 3
Classifier: License :: Other/Proprietary License
Classifier: Operating System :: OS Independent
Classifier: Development Status :: 5 - Production/Stable
Classifier: Intended Audience :: Developers
Classifier: Topic :: Software Development :: Build Tools
